drb/signatures/magic/__init__.py
drb/signatures/magic/_version.py
drb/signatures/magic/drb_signature_magic.py
drb/signatures/magic/execptions.py
drb_signature_magic-1.0.0.data/data/requirements.txt
drb_signature_magic-1.0.0.dist-info/METADATA
drb_signature_magic-1.0.0.dist-info/WHEEL
drb_signature_magic-1.0.0.dist-info/entry_points.txt
drb_signature_magic-1.0.0.dist-info/top_level.txt
drb_signature_magic-1.0.0.dist-info/RECORD
