Metadata-Version: 2.1
Name: drb-signature-magic
Version: 1.0.0
Summary: DRB Magic Signature
Home-page: https://gitlab.com/drb-python/singature/magic
Author: GAEL Systems
Author-email: drb-python@gael.fr
License: UNKNOWN
Project-URL: Documentation, https://drb-python.gitlab.io/singature/magic
Project-URL: Source, https://gitlab.com/drb-python/signature/magic
Platform: UNKNOWN
Classifier: Programming Language :: Python :: 3.8
Classifier: License :: OSI Approved :: Apache Software License
Classifier: Operating System :: OS Independent
Requires-Python: >=3.8
Requires-Dist: drb (==2.0.*)
